devex_sdk/__init__.py
devex_sdk/add.py
devex_sdk/subtract.py
devex_sdk/bucketization/__init__.py
devex_sdk/bucketization/bucketization.py
devex_sdk/circles/__init__.py
devex_sdk/circles/circles.py
devex_sdk/data_ingestion/__init__.py
devex_sdk/data_ingestion/eks_connector.py
devex_sdk/data_ingestion/gz_connector.py
devex_sdk/data_ingestion/nested_json_connector.py
devex_sdk/data_ingestion/pandas_data_connector.py
devex_sdk/data_ingestion/spark_config.ini
devex_sdk/data_ingestion/spark_data_connector.py
devex_sdk/data_ingestion/spark_utils.py
devex_sdk/data_ingestion/container_insights_schema/Cluster.json
devex_sdk/data_ingestion/container_insights_schema/ClusterNamespace.json
devex_sdk/data_ingestion/container_insights_schema/ClusterService.json
devex_sdk/data_ingestion/container_insights_schema/Container.json
devex_sdk/data_ingestion/container_insights_schema/ContainerFS.json
devex_sdk/data_ingestion/container_insights_schema/Node.json
devex_sdk/data_ingestion/container_insights_schema/NodeDiskIO.json
devex_sdk/data_ingestion/container_insights_schema/NodeFS.json
devex_sdk/data_ingestion/container_insights_schema/NodeNet.json
devex_sdk/data_ingestion/container_insights_schema/Pod.json
devex_sdk/data_ingestion/container_insights_schema/PodNet.json
devex_sdk/data_ingestion/container_insights_schema/__init__.py
devex_sdk/data_ingestion/container_insights_schema/eks_raw_pyspark_schema.py
devex_sdk/extras/__init__.py
devex_sdk/extras/divide.py
devex_sdk/extras/multiply.py
devex_sdk/feature_engine/__init__.py
devex_sdk/feature_engine/feature_extractor.py
devex_sdk/feature_engine/eks_feature_store/container_autoencoder_ad_features.json
devex_sdk/feature_engine/eks_feature_store/container_pca_ad_features.json
devex_sdk/feature_engine/eks_feature_store/node_autoencoder_ad_features.json
devex_sdk/feature_engine/eks_feature_store/node_hmm_ad_features.json
devex_sdk/feature_engine/eks_feature_store/node_pca_ad_features.json
devex_sdk-1.0.4.dist-info/LICENSE.txt
devex_sdk-1.0.4.dist-info/METADATA
devex_sdk-1.0.4.dist-info/WHEEL
devex_sdk-1.0.4.dist-info/top_level.txt
devex_sdk-1.0.4.dist-info/RECORD
