Metadata-Version: 2.1
Name: devex-sdk
Version: 1.0.4
Summary: Dish DevEx open source SDK
Home-page: https://git-codecommit.us-west-2.amazonaws.com/v1/repos/devex_sdk
Author-email: devex@dish.com
License: Dish Wireless
License-File: LICENSE.txt
Requires-Dist: pyspark
Requires-Dist: pandas
Requires-Dist: numpy
Requires-Dist: tqdm
Requires-Dist: configparser
Requires-Dist: dask
Requires-Dist: boto3
Requires-Dist: fastparquet
Requires-Dist: pyarrow
